<?xml version="1.0" encoding="UTF-8"?>
<!DOCTYPE struts PUBLIC
   "-//Apache Software Foundation//DTD Struts Configuration 2.0//EN"
   "http://struts.apache.org/dtds/struts-2.0.dtd">

   <struts>
   	<constant name="struts.devMode" value="true"/>
	   <package name="profiling" extends="struts-default, json-default">
	  	   		 
		   <interceptors>
		   		<interceptor-stack name="myStack">
		   			<interceptor-ref name="defaultStack"/>
		   			<interceptor-ref name="fileUpload"/>
		   			<interceptor-ref name="json">
		   				<param name="enableSMD">true</param>
		   			</interceptor-ref>
		   		</interceptor-stack>
		   	</interceptors>
		   	
		   	<action name="upload_Achievement_Certificate" 
	  				class="com.action.profiling.Insert_Achievement_Certificate">
	  				<interceptor-ref name="myStack"/>
	  			<result name="success" type="json">
	  				<param name="">acModel</param>
	  			</result>
	  			<result name="input" type="json">
		  			<param name="statusCode">500</param>
		  			<param name="errorCode">500</param>
		  		</result>
	  			
	  		</action>
	  	
	  		<action name="uploadProject" class="com.action.profiling.Insert_Project">
	  			<interceptor-ref name="myStack"/>
		  		<result name="success" type="json">
		  			<param name="">pModel</param>
		  		</result>
		  		<result name="input" type="json">
		  			<param name="statusCode">500</param>
		  			<param name="errorCode">500</param>
		  		</result>
	  		</action>
	  		
	  		<action name="uploadResearch" class="com.action.profiling.Insert_Research">
	  			<interceptor-ref name="myStack"/>
		  		<result name="success" type="json">
		  			<param name="">rModel</param>
		  		</result>
		  		<result name="input" type="json">
		  			<param name="statusCode">500</param>
		  			<param name="errorCode">500</param>
		  		</result>
	  		</action>
	  	
	  		<action name="uploadResume" class="com.action.profiling.Insert_Resume">
	  			<result name="success" type="json">
	  				<param name="">rModel</param>
	  			</result>
	  			<result name="input" type="json">
		  			<param name="statusCode">500</param>
		  			<param name="errorCode">500</param>
		  		</result>
	  		</action>
	  		
	  		<action name="uploadUserImage" class="com.action.profiling.Upload_UserImageAction">	  			
	  			<interceptor-ref name="myStack"/>
	  			<result name="success" type="json">
	  			
	  			</result>
	  			<result name="input" type="json">
		  			<param name="statusCode">500</param>
		  			<param name="errorCode">500</param>
		  		</result>
	  		</action>
	  		
	  		<action name="updateUserProfile" class="com.action.profiling.Update_UserProfileAction">
	  			<interceptor-ref name="myStack"/>
	  			<result name="success" type="json">
	  				<param name="excludeNullProperties">true</param>
	  			</result>
	  			<result name="input" type="json">
		  			<param name="statusCode">500</param>
		  			<param name="errorCode">500</param>
		  		</result>
	  		</action>
	  		
	  		<action name="updateUserPassword" class="com.action.profiling.Update_UserPasswordAction">
	  			<interceptor-ref name="myStack"/>
	  			<result name="success" type="json">
	  			</result>
	  			<result name="input" type="json">
		  			<param name="statusCode">500</param>
		  			<param name="errorCode">500</param>
		  		</result>
	  		</action>
	  		
	  		<action name="updateCurrentSession" class="com.action.profiling.Update_CurrentSessionAction">
	  			<interceptor-ref name="myStack"/>
	  			<result name="success" type="json">
	  				<param name="excludeNullProperties">true</param>
	  			</result>
	  			<result name="input" type="json">
		  			<param name="statusCode">500</param>
		  			<param name="errorCode">500</param>
		  		</result>
	  		</action>
	  		
	  		<action name="View_Achievements_Certifications" 
	  			class="com.action.profiling.View_Achievements_Certifications">
	  			<interceptor-ref name="myStack"/>
	  			<result name="success" type="json">
	  				<param name="excludeNullProperties">true</param>
	  			</result>
	  			<result name="input" type="json">
		  			<param name="statusCode">500</param>
		  			<param name="errorCode">500</param>
		  		</result>
	  		</action>
	  		<action name="View_Projects" class="com.action.profiling.View_Projects">
	  			<interceptor-ref name="myStack"/>
	  			<result name="success" type="json">
	  				<param name="excludeNullProperties">true</param>
	  			</result>
	  			<result name="input" type="json">
		  			<param name="statusCode">500</param>
		  			<param name="errorCode">500</param>
		  		</result>
	  		</action>
	  		<action name="View_Researches" class="com.action.profiling.View_Researches">
	  			<interceptor-ref name="myStack"/>
	  			<result name="success" type="json">
	  				<param name="excludeNullProperties">true</param>
	  			</result>
	  			<result name="input" type="json">
		  			<param name="statusCode">500</param>
		  			<param name="errorCode">500</param>
		  		</result>
	  		</action>
	  		<action name="View_Resume" class="com.action.profiling.View_Resume">
	  			<interceptor-ref name="myStack"/>
	  			<result name="success" type="json">
	  				<param name="excludeNullProperties">true</param>
	  			</result>
	  			<result name="input" type="json">
		  			<param name="statusCode">500</param>
		  			<param name="errorCode">500</param>
		  		</result>
	  		</action>
	  		<action name="generatePDF" class="com.action.profiling.Generate_PDF">
	  			<interceptor-ref name="myStack"/>
	  			<result name="success" type="json">
	  				<param name="excludeNullProperties">true</param>
	  			</result>
	  			<result name="input" type="json">
		  			<param name="statusCode">500</param>
		  			<param name="errorCode">500</param>
		  		</result>
	  		</action>
	  		<action name="Delete_Achievements_Certifications" 
	  			class="com.action.profiling.Delete_Achievements_Certifications">
	  			<interceptor-ref name="myStack"/>
	  			<result name="success" type="json">
	  				<param name="excludeNullProperties">true</param>
	  			</result>
	  			<result name="input" type="json">
		  			<param name="statusCode">500</param>
		  			<param name="errorCode">500</param>
		  		</result>
	  		</action>
	  		<action name="Delete_Project" 
	  			class="com.action.profiling.Delete_Project">
	  			<interceptor-ref name="myStack"/>
	  			<result name="success" type="json">
	  				<param name="excludeNullProperties">true</param>
	  			</result>
	  			<result name="input" type="json">
		  			<param name="statusCode">500</param>
		  			<param name="errorCode">500</param>
		  		</result>
	  		</action>
	  		<action name="Delete_Research" 
	  			class="com.action.profiling.Delete_Research">
	  			<interceptor-ref name="myStack"/>
	  			<result name="success" type="json">
	  				<param name="excludeNullProperties">true</param>
	  			</result>
	  			<result name="input" type="json">
		  			<param name="statusCode">500</param>
		  			<param name="errorCode">500</param>
		  		</result>
	  		</action>
	  		<action name="Delete_Resume" 
	  			class="com.action.profiling.Delete_Resume">
	  			<interceptor-ref name="myStack"/>
	  			<result name="success" type="json">
	  				<param name="excludeNullProperties">true</param>
	  			</result>
	  			<result name="input" type="json">
		  			<param name="statusCode">500</param>
		  			<param name="errorCode">500</param>
		  		</result>
	  		</action>
	  		
	
	  	</package>
   </struts>